README.md
setup.cfg
setup.py
ejercicio13/__init__.py
ejercicio13/operaciones.py
ejercicio13_camaljac.egg-info/PKG-INFO
ejercicio13_camaljac.egg-info/SOURCES.txt
ejercicio13_camaljac.egg-info/dependency_links.txt
ejercicio13_camaljac.egg-info/top_level.txt
tests/__init__.py
tests/test_operaciones.py