Metadata-Version: 2.4
Name: ejercicio13-camaljac
Version: 0.1.0
Summary: Un módulo simple para operaciones matemáticas básicas.
Author: camaljac
Author-email: camaljac@gmail.com
License: MIT
Keywords: calculadora matematicas suma resta multiplicacion division
Classifier: Programming Language :: Python :: 3
Classifier: License :: OSI Approved :: MIT License
Classifier: Operating System :: OS Independent
Classifier: Development Status :: 3 - Alpha
Classifier: Intended Audience :: Developers
Classifier: Topic :: Software Development :: Build Tools
Requires-Python: >=3.8
Dynamic: author
Dynamic: author-email
Dynamic: classifier
Dynamic: description
Dynamic: description-content-type
Dynamic: keywords
Dynamic: requires-python
Dynamic: summary
